{"description":"gb1_st2023_-_perorangan","dataKey":"gb1_st2023_-_perorangan","predata":[{"dataKey":"level_1","answer":"32"},{"dataKey":"level_2","answer":"13"},{"dataKey":"level_3","answer":"081"},{"dataKey":"level_4","answer":"002"},{"dataKey":"level_5","answer":"004B"},{"dataKey":"cawi_identifier","answer":""},{"dataKey":"cawi_pin","answer":""},{"dataKey":"lat","answer":""},{"dataKey":"long","answer":""},{"dataKey":"status_sample","answer":"PRIMARY"},{"dataKey":"strata","answer":""},{"dataKey":"email","answer":""},{"dataKey":"l1_r101","answer":"JAWA BARAT"},{"dataKey":"l1_r102","answer":"SUBANG"},{"dataKey":"l1_r103","answer":"DAWUAN"},{"dataKey":"l1_r104","answer":"MARGASARI"},{"dataKey":"l1_r105","answer":"2"},{"dataKey":"l1_r106","answer":"004B"},{"dataKey":"kode_sls","answer":"001300"},{"dataKey":"l1_r501","answer":"RT 012 RW 005 DUSUN 003"},{"dataKey":"l1_r502","answer":"50"},{"dataKey":"no_kk_tani","answer":""},{"dataKey":"l1_r505","answer":"1"},{"dataKey":"l1_r503","answer":"OOP SOPIAN "},{"dataKey":"l1_nmkk_artlain","answer":"OOP SOPIAN  /  KARNETI"},{"dataKey":"l1_r504","answer":"KP BUAH DUA"},{"dataKey":"identitas","answer":""},{"dataKey":"l1_r505a","answer":"0"},{"dataKey":"pasangan","answer":" KARNETI"},{"dataKey":"flag_tani","answer":""},{"dataKey":"metode","answer":"Door to Door"},{"dataKey":"kd_metode","answer":""},{"dataKey":"l1_r107","answer":"RT 012 RW 005 DUSUN 003, RT 014 RW 006 DUSUN 003"},{"dataKey":"kode_slss","answer":""},{"dataKey":"nik","answer":"3210262005730001 "},{"dataKey":"nik_pasangan","answer":" 3213275703750003"},{"dataKey":"nomor_kk","answer":""}]}